LICENSE
MANIFEST.in
README
requirements.txt
setup.py
catsoop/__init__.py
catsoop/api.py
catsoop/auth.py
catsoop/base_context.py
catsoop/check.py
catsoop/debug_log.py
catsoop/dev.hash
catsoop/dispatch.py
catsoop/emoji.py
catsoop/errors.py
catsoop/groups.py
catsoop/language.py
catsoop/loader.py
catsoop/lti.py
catsoop/mail.py
catsoop/main.py
catsoop/markdown.py
catsoop/process.py
catsoop/session.py
catsoop/time.py
catsoop/tutor.py
catsoop/user.py
catsoop/util.py
catsoop/wsgi.py
catsoop.egg-info/PKG-INFO
catsoop.egg-info/SOURCES.txt
catsoop.egg-info/dependency_links.txt
catsoop.egg-info/entry_points.txt
catsoop.egg-info/requires.txt
catsoop.egg-info/top_level.txt
catsoop/__AUTH__/cas/cas.py
catsoop/__AUTH__/cas/callback/content.py
catsoop/__AUTH__/cas/callback/preload.py
catsoop/__AUTH__/cert/cert.py
catsoop/__AUTH__/dummy/dummy.py
catsoop/__AUTH__/ldap3/ldap3.py
catsoop/__AUTH__/login/login.py
catsoop/__AUTH__/login/__STATIC__/cs_hash.js
catsoop/__AUTH__/openid_connect/openid_connect.py
catsoop/__AUTH__/openid_connect/callback/content.py
catsoop/__AUTH__/openid_connect/callback/preload.py
catsoop/__AUTH__/sso/sso.py
catsoop/__AUTH__/sso/callback/content.py
catsoop/__AUTH__/sso/callback/preload.py
catsoop/__HANDLERS__/default/default.py
catsoop/__HANDLERS__/default/__STATIC__/cs_ajax.js
catsoop/__HANDLERS__/default/__STATIC__/cs_groups.js
catsoop/__HANDLERS__/default/__STATIC__/cs_timer.js
catsoop/__HANDLERS__/handout/handout.py
catsoop/__HANDLERS__/passthrough/passthrough.py
catsoop/__HANDLERS__/raw_response/raw_response.py
catsoop/__HANDLERS__/redirect/redirect.py
catsoop/__QTYPES__/bigbox/bigbox.py
catsoop/__QTYPES__/checkoff/checkoff.py
catsoop/__QTYPES__/expression/expression.py
catsoop/__QTYPES__/expression/__SYNTAX__/base.py
catsoop/__QTYPES__/expression/__SYNTAX__/python.py
catsoop/__QTYPES__/fileupload/fileupload.py
catsoop/__QTYPES__/multiexpression/multiexpression.py
catsoop/__QTYPES__/multiplechoice/multiplechoice.py
catsoop/__QTYPES__/number/number.py
catsoop/__QTYPES__/pythoncode/pythoncode.py
catsoop/__QTYPES__/pythoncode/__SANDBOXES__/_template
catsoop/__QTYPES__/pythoncode/__SANDBOXES__/base.py
