Metadata-Version: 2.1
Name: catsoop
Version: 2021.2.0
Summary: CAT-SOOP is a tool for automatic collection and assessment of online exercises.
Home-page: https://catsoop.mit.edu
Author: CAT-SOOP Contributors
Author-email: catsoop-dev@mit.edu
License: AGPLv3+
Platform: UNKNOWN
Classifier: Development Status :: 4 - Beta
Classifier: Intended Audience :: Education
Classifier: License :: OSI Approved :: GNU Affero General Public License v3 or later (AGPLv3+)
Classifier: Programming Language :: Python :: 3.6
Classifier: Programming Language :: Python :: 3.7
Classifier: Programming Language :: Python :: 3.8
Classifier: Topic :: Education
Classifier: Topic :: Internet :: WWW/HTTP :: WSGI
Provides-Extra: postgres
Provides-Extra: test
